pbdg/__init__.py
pbdg/common.py
pbdg/events.py
pbdg/features.py
pbdg/main.py
pbdg/options.py
players_behaviors_dataset_generator-0.1.2.dist-info/LICENSE
players_behaviors_dataset_generator-0.1.2.dist-info/METADATA
players_behaviors_dataset_generator-0.1.2.dist-info/WHEEL
players_behaviors_dataset_generator-0.1.2.dist-info/entry_points.txt
players_behaviors_dataset_generator-0.1.2.dist-info/top_level.txt
players_behaviors_dataset_generator-0.1.2.dist-info/RECORD
