Metadata-Version: 2.1
Name: players-behaviors-dataset-generator
Version: 0.1.2
Summary: A simple comand line tool to create game datasets for analytics and machine learning use cases
Home-page: https://github.com/awslabs/players-behaviors-dataset-generator
Author: Frederic Nowak
Author-email: fredenow@amazon.com
Project-URL: Project Tracker, https://github.com/awslabs/players-behaviors-dataset-generator/projects
Project-URL: Issue Tracker, https://github.com/awslabs/players-behaviors-dataset-generator/issues
Keywords: game machine learning analytics dataset generator player behaviour
Classifier: Topic :: Utilities
Classifier: Programming Language :: Python :: 3
Classifier: License :: OSI Approved :: MIT No Attribution License (MIT-0)
Classifier: Operating System :: OS Independent
Requires-Python: >=3.6
License-File: LICENSE
Requires-Dist: click
Requires-Dist: numpy
Requires-Dist: pandas
Requires-Dist: matplotlib
